MultiEnvEmployer/__init__.py
MultiEnvEmployer/employer/MessageReader.py
MultiEnvEmployer/employer/OutputHandler.py
MultiEnvEmployer/employer/UReturnIterator.py
MultiEnvEmployer/employer/Watchdog.py
MultiEnvEmployer/employer/YieldIterator.py
MultiEnvEmployer/employer/employer.py
MultiEnvEmployer/remote/remote_module.py
MultiEnvEmployer/utils/CacheAppDirs.py
MultiEnvEmployer/utils/FileCache.py
MultiEnvEmployer/utils/errors.py
MultiEnvEmployer/worker/introspection.py
MultiEnvEmployer/worker/worker.py
multi_env_employer-1.0.1.dist-info/licenses/LICENSE
multi_env_employer-1.0.1.dist-info/METADATA
multi_env_employer-1.0.1.dist-info/WHEEL
multi_env_employer-1.0.1.dist-info/top_level.txt
multi_env_employer-1.0.1.dist-info/RECORD
