Metadata-Version: 2.4
Name: multi-env-employer
Version: 1.0.1
Summary: A library for calling functions and generators from Python modules located in other virtual environments, including environments with different Python versions and conflicting dependencies.
Author-email: REYIL <azamatilbulov@gmail.com>
License: MIT License
Project-URL: Homepage, https://github.com/REYIL/MultiEnvEmployer
Project-URL: Repository, https://github.com/REYIL/MultiEnvEmployer
Project-URL: Issues, https://github.com/REYIL/MultiEnvEmployer/issues
Classifier: Development Status :: 4 - Beta
Classifier: Intended Audience :: Developers
Classifier: Topic :: Software Development :: Libraries
Classifier: Topic :: System :: Distributed Computing
Classifier: Topic :: Software Development :: Build Tools
Classifier: License :: OSI Approved :: MIT License
Classifier: Programming Language :: Python :: 3
Classifier: Operating System :: OS Independent
Requires-Python: >=3.8
License-File: LICENSE
Dynamic: license-file
